{"47": {"start": 0, "end": 9}, "90": {"start": 0, "end": 9}, "28": {"start": 0, "end": 9}, "41": {"start": 0, "end": 9}, "65": {"start": 0, "end": 9}, "70": {"start": 0, "end": 9}, "134": {"start": 0, "end": 9}, "50": {"start": 0, "end": 9}, "92": {"start": 0, "end": 9}, "122": {"start": 0, "end": 9}, "20": {"start": 0, "end": 9}, "67": {"start": 0, "end": 9}, "71": {"start": 0, "end": 9}, "117": {"start": 0, "end": 9}, "96": {"start": 0, "end": 9}, "112": {"start": 0, "end": 9}, "128": {"start": 0, "end": 9}, "38": {"start": 0, "end": 9}, "139": {"start": 0, "end": 9}, "110": {"start": 0, "end": 9}, "132": {"start": 0, "end": 9}, "57": {"start": 0, "end": 9}, "99": {"start": 0, "end": 9}, "127": {"start": 0, "end": 9}, "6": {"start": 0, "end": 9}, "4": {"start": 0, "end": 9}, "119": {"start": 1, "end": 3}}