{"(80,5599.json)": {"start": 2, "end": null}, "(31,5599.json)": {"start": 2, "end": null}, "(9,5599.json)": {"start": 2, "end": null}, "(80,5088.json)": {"start": 5, "end": 5}, "(31,5088.json)": {"start": 5, "end": 5}, "(9,5088.json)": {"start": 5, "end": 5}, "(138,4602.json)": {"start": 6, "end": null}, "(114,4602.json)": {"start": 6, "end": null}, "(145,4602.json)": {"start": 6, "end": null}, "(86,4602.json)": {"start": 6, "end": null}, "(88,4602.json)": {"start": 6, "end": null}, "(92,4602.json)": {"start": 6, "end": null}, "(100,4602.json)": {"start": 6, "end": null}, "(51,4602.json)": {"start": 6, "end": null}, "(2,4602.json)": {"start": 6, "end": null}, "(117,4602.json)": {"start": 6, "end": null}, "(46,4602.json)": {"start": 6, "end": null}, "(59,4602.json)": {"start": 6, "end": null}, "(0,4602.json)": {"start": 6, "end": null}, "(33,4602.json)": {"start": 6, "end": null}, "(16,4602.json)": {"start": 6, "end": null}, "(78,4602.json)": {"start": 6, "end": null}, "(124,4602.json)": {"start": 6, "end": null}, "(73,4602.json)": {"start": 6, "end": null}, "(23,4602.json)": {"start": 6, "end": null}, "(89,4602.json)": {"start": 6, "end": null}, "(140,4602.json)": {"start": 6, "end": null}, "(20,4602.json)": {"start": 6, "end": null}, "(118,4602.json)": {"start": 6, "end": null}, "(97,4602.json)": {"start": 6, "end": null}, "(80,4722.json)": {"start": 7, "end": null}, "(31,4722.json)": {"start": 7, "end": null}, "(9,4722.json)": {"start": 7, "end": null}, "(80,10498.json)": {"start": 8, "end": null}, "(31,10498.json)": {"start": 8, "end": null}, "(9,10498.json)": {"start": 8, "end": null}, "(138,7398.json)": {"start": 9, "end": null}, "(114,7398.json)": {"start": 9, "end": null}, "(145,7398.json)": {"start": 9, "end": null}, "(86,7398.json)": {"start": 9, "end": null}, "(88,7398.json)": {"start": 9, "end": null}, "(92,7398.json)": {"start": 9, "end": null}, "(100,7398.json)": {"start": 9, "end": null}, "(51,7398.json)": {"start": 9, "end": null}, "(2,7398.json)": {"start": 9, "end": null}, "(117,7398.json)": {"start": 9, "end": null}, "(46,7398.json)": {"start": 9, "end": null}, "(59,7398.json)": {"start": 9, "end": null}, "(0,7398.json)": {"start": 9, "end": null}, "(33,7398.json)": {"start": 9, "end": null}, "(16,7398.json)": {"start": 9, "end": null}, "(78,7398.json)": {"start": 9, "end": null}, "(80,12781.json)": {"start": 9, "end": null}, "(124,7398.json)": {"start": 9, "end": null}, "(31,12781.json)": {"start": 9, "end": null}, "(73,7398.json)": {"start": 9, "end": null}, "(23,7398.json)": {"start": 9, "end": null}, "(89,7398.json)": {"start": 9, "end": null}, "(140,7398.json)": {"start": 9, "end": null}, "(9,12781.json)": {"start": 9, "end": null}, "(20,7398.json)": {"start": 9, "end": null}, "(118,7398.json)": {"start": 9, "end": null}, "(97,7398.json)": {"start": 9, "end": null}, "(138,3670.json)": {"start": 10, "end": null}, "(114,3670.json)": {"start": 10, "end": null}, "(145,3670.json)": {"start": 10, "end": null}, "(86,3670.json)": {"start": 10, "end": null}, "(88,3670.json)": {"start": 10, "end": null}, "(92,3670.json)": {"start": 10, "end": null}, "(100,3670.json)": {"start": 10, "end": null}, "(51,3670.json)": {"start": 10, "end": null}, "(2,3670.json)": {"start": 10, "end": null}, "(117,3670.json)": {"start": 10, "end": null}, "(46,3670.json)": {"start": 10, "end": null}, "(59,3670.json)": {"start": 10, "end": null}, "(0,3670.json)": {"start": 10, "end": null}, "(33,3670.json)": {"start": 10, "end": null}, "(16,3670.json)": {"start": 10, "end": null}, "(78,3670.json)": {"start": 10, "end": null}, "(80,3796.json)": {"start": 10, "end": null}, "(124,3670.json)": {"start": 10, "end": null}, "(31,3796.json)": {"start": 10, "end": null}, "(73,3670.json)": {"start": 10, "end": null}, "(23,3670.json)": {"start": 10, "end": null}, "(89,3670.json)": {"start": 10, "end": null}, "(140,3670.json)": {"start": 10, "end": null}, "(9,3796.json)": {"start": 10, "end": null}, "(20,3670.json)": {"start": 10, "end": null}, "(118,3670.json)": {"start": 10, "end": null}, "(97,3670.json)": {"start": 10, "end": null}, "(138,4732.json)": {"start": 11, "end": 11}, "(114,4732.json)": {"start": 11, "end": 11}, "(145,4732.json)": {"start": 11, "end": 11}, "(86,4732.json)": {"start": 11, "end": 11}, "(88,4732.json)": {"start": 11, "end": 11}, "(92,4732.json)": {"start": 11, "end": 11}, "(100,4732.json)": {"start": 11, "end": 11}, "(51,4732.json)": {"start": 11, "end": 11}, "(2,4732.json)": {"start": 11, "end": 11}, "(117,4732.json)": {"start": 11, "end": 11}, "(46,4732.json)": {"start": 11, "end": 11}, "(59,4732.json)": {"start": 11, "end": 11}, "(0,4732.json)": {"start": 11, "end": 11}, "(33,4732.json)": {"start": 11, "end": 11}, "(16,4732.json)": {"start": 11, "end": 11}, "(78,4732.json)": {"start": 11, "end": 11}, "(80,11776.json)": {"start": 11, "end": null}, "(124,4732.json)": {"start": 11, "end": 11}, "(31,11776.json)": {"start": 11, "end": null}, "(73,4732.json)": {"start": 11, "end": 11}, "(23,4732.json)": {"start": 11, "end": 11}, "(89,4732.json)": {"start": 11, "end": 11}, "(140,4732.json)": {"start": 11, "end": 11}, "(9,11776.json)": {"start": 11, "end": null}, "(20,4732.json)": {"start": 11, "end": 11}, "(118,4732.json)": {"start": 11, "end": 11}, "(97,4732.json)": {"start": 11, "end": 11}, "(80,8445.json)": {"start": 12, "end": null}, "(31,8445.json)": {"start": 12, "end": null}, "(9,8445.json)": {"start": 12, "end": null}, "(138,5235.json)": {"start": 13, "end": 13}, "(114,5235.json)": {"start": 13, "end": 13}, "(145,5235.json)": {"start": 13, "end": 13}, "(86,5235.json)": {"start": 13, "end": 13}, "(88,5235.json)": {"start": 13, "end": 13}, "(92,5235.json)": {"start": 13, "end": 13}, "(100,5235.json)": {"start": 13, "end": 13}, "(51,5235.json)": {"start": 13, "end": 13}, "(2,5235.json)": {"start": 13, "end": 13}, "(117,5235.json)": {"start": 13, "end": 13}, "(46,5235.json)": {"start": 13, "end": 13}, "(59,5235.json)": {"start": 13, "end": 13}, "(0,5235.json)": {"start": 13, "end": 13}, "(33,5235.json)": {"start": 13, "end": 13}, "(16,5235.json)": {"start": 13, "end": 13}, "(78,5235.json)": {"start": 13, "end": 13}, "(124,5235.json)": {"start": 13, "end": 13}, "(73,5235.json)": {"start": 13, "end": 13}, "(23,5235.json)": {"start": 13, "end": 13}, "(89,5235.json)": {"start": 13, "end": 13}, "(140,5235.json)": {"start": 13, "end": 13}, "(20,5235.json)": {"start": 13, "end": 13}, "(118,5235.json)": {"start": 13, "end": 13}, "(97,5235.json)": {"start": 13, "end": 13}}