{"(113,689.json)": {"start": 0, "end": null}, "(129,689.json)": {"start": 0, "end": null}, "(68,689.json)": {"start": 0, "end": null}, "(138,689.json)": {"start": 0, "end": null}, "(76,689.json)": {"start": 0, "end": null}, "(32,689.json)": {"start": 0, "end": null}, "(113,13359.json)": {"start": 1, "end": null}, "(129,13359.json)": {"start": 1, "end": null}, "(68,13359.json)": {"start": 1, "end": null}, "(138,13359.json)": {"start": 1, "end": null}, "(76,13359.json)": {"start": 1, "end": null}, "(32,13359.json)": {"start": 1, "end": null}, "(36,11788.json)": {"start": 3, "end": 3}, "(19,11788.json)": {"start": 3, "end": 3}, "(96,11788.json)": {"start": 3, "end": 3}, "(4,11788.json)": {"start": 3, "end": 3}, "(82,11788.json)": {"start": 3, "end": 3}, "(24,11788.json)": {"start": 3, "end": 3}, "(50,11788.json)": {"start": 3, "end": 3}, "(52,11788.json)": {"start": 3, "end": 3}, "(110,11788.json)": {"start": 3, "end": 3}, "(131,11788.json)": {"start": 3, "end": 3}, "(69,11788.json)": {"start": 3, "end": 3}, "(100,11788.json)": {"start": 3, "end": 3}, "(92,11788.json)": {"start": 3, "end": 3}, "(127,11788.json)": {"start": 3, "end": 3}, "(125,11788.json)": {"start": 3, "end": 3}, "(122,11788.json)": {"start": 3, "end": 3}, "(49,11788.json)": {"start": 3, "end": 3}, "(34,11788.json)": {"start": 3, "end": 3}, "(2,11788.json)": {"start": 3, "end": 3}, "(95,11788.json)": {"start": 3, "end": 3}, "(117,11788.json)": {"start": 3, "end": 3}, "(113,9204.json)": {"start": 7, "end": null}, "(129,9204.json)": {"start": 7, "end": null}, "(68,9204.json)": {"start": 7, "end": null}, "(138,9204.json)": {"start": 7, "end": null}, "(76,9204.json)": {"start": 7, "end": null}, "(32,9204.json)": {"start": 7, "end": null}, "(36,9206.json)": {"start": 11, "end": null}, "(19,9206.json)": {"start": 11, "end": null}, "(96,9206.json)": {"start": 11, "end": null}, "(4,9206.json)": {"start": 11, "end": null}, "(82,9206.json)": {"start": 11, "end": null}, "(24,9206.json)": {"start": 11, "end": null}, "(50,9206.json)": {"start": 11, "end": null}, "(52,9206.json)": {"start": 11, "end": null}, "(110,9206.json)": {"start": 11, "end": null}, "(131,9206.json)": {"start": 11, "end": null}, "(69,9206.json)": {"start": 11, "end": null}, "(100,9206.json)": {"start": 11, "end": null}, "(92,9206.json)": {"start": 11, "end": null}, "(127,9206.json)": {"start": 11, "end": null}, "(125,9206.json)": {"start": 11, "end": null}, "(122,9206.json)": {"start": 11, "end": null}, "(49,9206.json)": {"start": 11, "end": null}, "(34,9206.json)": {"start": 11, "end": null}, "(2,9206.json)": {"start": 11, "end": null}, "(95,9206.json)": {"start": 11, "end": null}, "(117,9206.json)": {"start": 11, "end": null}, "(113,10072.json)": {"start": 14, "end": null}, "(129,10072.json)": {"start": 14, "end": null}, "(68,10072.json)": {"start": 14, "end": null}, "(138,10072.json)": {"start": 14, "end": null}, "(76,10072.json)": {"start": 14, "end": null}, "(32,10072.json)": {"start": 14, "end": null}}