{"(64,10692.json)": {"start": 0, "end": null}, "(133,10692.json)": {"start": 0, "end": null}, "(14,10692.json)": {"start": 0, "end": null}, "(77,10692.json)": {"start": 0, "end": null}, "(106,10692.json)": {"start": 0, "end": null}, "(28,10692.json)": {"start": 0, "end": null}, "(76,10692.json)": {"start": 0, "end": null}, "(17,10692.json)": {"start": 0, "end": null}, "(13,10692.json)": {"start": 0, "end": null}, "(122,10692.json)": {"start": 0, "end": null}, "(64,2053.json)": {"start": 1, "end": null}, "(133,2053.json)": {"start": 1, "end": null}, "(14,2053.json)": {"start": 1, "end": null}, "(77,2053.json)": {"start": 1, "end": null}, "(106,2053.json)": {"start": 1, "end": null}, "(28,2053.json)": {"start": 1, "end": null}, "(76,2053.json)": {"start": 1, "end": null}, "(17,2053.json)": {"start": 1, "end": null}, "(13,2053.json)": {"start": 1, "end": null}, "(122,2053.json)": {"start": 1, "end": null}, "(4,11788.json)": {"start": 3, "end": 3}, "(47,11788.json)": {"start": 3, "end": 3}, "(38,11788.json)": {"start": 3, "end": 3}, "(105,11788.json)": {"start": 3, "end": 3}, "(119,11788.json)": {"start": 3, "end": 3}, "(83,11788.json)": {"start": 3, "end": 3}, "(84,11788.json)": {"start": 3, "end": 3}, "(78,11788.json)": {"start": 3, "end": 3}, "(121,11788.json)": {"start": 3, "end": 3}, "(26,11788.json)": {"start": 3, "end": 3}, "(91,11788.json)": {"start": 3, "end": 3}, "(9,11788.json)": {"start": 3, "end": 3}, "(94,11788.json)": {"start": 3, "end": 3}, "(93,11788.json)": {"start": 3, "end": 3}, "(110,11788.json)": {"start": 3, "end": 3}, "(142,11788.json)": {"start": 3, "end": 3}, "(125,11788.json)": {"start": 3, "end": 3}, "(64,11429.json)": {"start": 5, "end": 5}, "(133,11429.json)": {"start": 5, "end": 5}, "(14,11429.json)": {"start": 5, "end": 5}, "(77,11429.json)": {"start": 5, "end": 5}, "(106,11429.json)": {"start": 5, "end": 5}, "(28,11429.json)": {"start": 5, "end": 5}, "(76,11429.json)": {"start": 5, "end": 5}, "(17,11429.json)": {"start": 5, "end": 5}, "(13,11429.json)": {"start": 5, "end": 5}, "(122,11429.json)": {"start": 5, "end": 5}, "(64,9922.json)": {"start": 6, "end": null}, "(133,9922.json)": {"start": 6, "end": null}, "(14,9922.json)": {"start": 6, "end": null}, "(77,9922.json)": {"start": 6, "end": null}, "(106,9922.json)": {"start": 6, "end": null}, "(28,9922.json)": {"start": 6, "end": null}, "(76,9922.json)": {"start": 6, "end": null}, "(17,9922.json)": {"start": 6, "end": null}, "(13,9922.json)": {"start": 6, "end": null}, "(122,9922.json)": {"start": 6, "end": null}, "(4,9206.json)": {"start": 11, "end": null}, "(47,9206.json)": {"start": 11, "end": null}, "(38,9206.json)": {"start": 11, "end": null}, "(105,9206.json)": {"start": 11, "end": null}, "(119,9206.json)": {"start": 11, "end": null}, "(83,9206.json)": {"start": 11, "end": null}, "(84,9206.json)": {"start": 11, "end": null}, "(78,9206.json)": {"start": 11, "end": null}, "(121,9206.json)": {"start": 11, "end": null}, "(26,9206.json)": {"start": 11, "end": null}, "(91,9206.json)": {"start": 11, "end": null}, "(9,9206.json)": {"start": 11, "end": null}, "(94,9206.json)": {"start": 11, "end": null}, "(93,9206.json)": {"start": 11, "end": null}, "(110,9206.json)": {"start": 11, "end": null}, "(142,9206.json)": {"start": 11, "end": null}, "(125,9206.json)": {"start": 11, "end": null}, "(64,6369.json)": {"start": 14, "end": 14}, "(133,6369.json)": {"start": 14, "end": 14}, "(14,6369.json)": {"start": 14, "end": 14}, "(77,6369.json)": {"start": 14, "end": 14}, "(106,6369.json)": {"start": 14, "end": 14}, "(28,6369.json)": {"start": 14, "end": 14}, "(76,6369.json)": {"start": 14, "end": 14}, "(17,6369.json)": {"start": 14, "end": 14}, "(13,6369.json)": {"start": 14, "end": 14}, "(122,6369.json)": {"start": 14, "end": 14}}