{"(139,5415.json)": {"start": 2, "end": 2}, "(39,5415.json)": {"start": 2, "end": 2}, "(26,5415.json)": {"start": 2, "end": 2}, "(95,5415.json)": {"start": 2, "end": 2}, "(62,5415.json)": {"start": 2, "end": 2}, "(121,5415.json)": {"start": 2, "end": 2}, "(97,11788.json)": {"start": 3, "end": 3}, "(54,11788.json)": {"start": 3, "end": 3}, "(75,11788.json)": {"start": 3, "end": 3}, "(105,11788.json)": {"start": 3, "end": 3}, "(33,11788.json)": {"start": 3, "end": 3}, "(99,11788.json)": {"start": 3, "end": 3}, "(59,11788.json)": {"start": 3, "end": 3}, "(29,11788.json)": {"start": 3, "end": 3}, "(135,11788.json)": {"start": 3, "end": 3}, "(61,11788.json)": {"start": 3, "end": 3}, "(122,11788.json)": {"start": 3, "end": 3}, "(12,11788.json)": {"start": 3, "end": 3}, "(89,11788.json)": {"start": 3, "end": 3}, "(57,11788.json)": {"start": 3, "end": 3}, "(80,11788.json)": {"start": 3, "end": 3}, "(87,11788.json)": {"start": 3, "end": 3}, "(76,11788.json)": {"start": 3, "end": 3}, "(73,11788.json)": {"start": 3, "end": 3}, "(90,11788.json)": {"start": 3, "end": 3}, "(134,11788.json)": {"start": 3, "end": 3}, "(67,11788.json)": {"start": 3, "end": 3}, "(139,9350.json)": {"start": 7, "end": 7}, "(39,9350.json)": {"start": 7, "end": 7}, "(26,9350.json)": {"start": 7, "end": 7}, "(95,9350.json)": {"start": 7, "end": 7}, "(62,9350.json)": {"start": 7, "end": 7}, "(121,9350.json)": {"start": 7, "end": 7}, "(139,12738.json)": {"start": 11, "end": 11}, "(97,9206.json)": {"start": 11, "end": 11}, "(39,12738.json)": {"start": 11, "end": 11}, "(54,9206.json)": {"start": 11, "end": 11}, "(75,9206.json)": {"start": 11, "end": 11}, "(105,9206.json)": {"start": 11, "end": 11}, "(26,12738.json)": {"start": 11, "end": 11}, "(33,9206.json)": {"start": 11, "end": 11}, "(99,9206.json)": {"start": 11, "end": 11}, "(59,9206.json)": {"start": 11, "end": 11}, "(95,12738.json)": {"start": 11, "end": 11}, "(29,9206.json)": {"start": 11, "end": 11}, "(62,12738.json)": {"start": 11, "end": 11}, "(135,9206.json)": {"start": 11, "end": 11}, "(61,9206.json)": {"start": 11, "end": 11}, "(122,9206.json)": {"start": 11, "end": 11}, "(12,9206.json)": {"start": 11, "end": 11}, "(89,9206.json)": {"start": 11, "end": 11}, "(57,9206.json)": {"start": 11, "end": 11}, "(80,9206.json)": {"start": 11, "end": 11}, "(87,9206.json)": {"start": 11, "end": 11}, "(76,9206.json)": {"start": 11, "end": 11}, "(121,12738.json)": {"start": 11, "end": 11}, "(73,9206.json)": {"start": 11, "end": 11}, "(90,9206.json)": {"start": 11, "end": 11}, "(134,9206.json)": {"start": 11, "end": 11}, "(67,9206.json)": {"start": 11, "end": 11}}