{"(44,2332.json)": {"start": 0, "end": null}, "(141,2332.json)": {"start": 0, "end": null}, "(95,2332.json)": {"start": 0, "end": null}, "(26,2332.json)": {"start": 0, "end": null}, "(108,2332.json)": {"start": 0, "end": null}, "(140,2332.json)": {"start": 0, "end": null}, "(84,2332.json)": {"start": 0, "end": null}, "(137,2332.json)": {"start": 0, "end": null}, "(112,2332.json)": {"start": 0, "end": null}, "(8,2332.json)": {"start": 0, "end": null}, "(29,2332.json)": {"start": 0, "end": null}, "(25,2332.json)": {"start": 0, "end": null}, "(118,2332.json)": {"start": 0, "end": null}, "(65,2332.json)": {"start": 0, "end": null}, "(119,2332.json)": {"start": 0, "end": null}, "(78,2332.json)": {"start": 0, "end": null}, "(71,2332.json)": {"start": 0, "end": null}, "(106,2332.json)": {"start": 0, "end": null}, "(80,2332.json)": {"start": 0, "end": null}, "(45,2332.json)": {"start": 0, "end": null}, "(129,2332.json)": {"start": 0, "end": null}, "(44,7903.json)": {"start": 3, "end": 3}, "(117,7760.json)": {"start": 3, "end": null}, "(141,7903.json)": {"start": 3, "end": 3}, "(95,7903.json)": {"start": 3, "end": 3}, "(26,7903.json)": {"start": 3, "end": 3}, "(108,7903.json)": {"start": 3, "end": 3}, "(140,7903.json)": {"start": 3, "end": 3}, "(84,7903.json)": {"start": 3, "end": 3}, "(137,7903.json)": {"start": 3, "end": 3}, "(112,7903.json)": {"start": 3, "end": 3}, "(8,7903.json)": {"start": 3, "end": 3}, "(92,7760.json)": {"start": 3, "end": null}, "(29,7903.json)": {"start": 3, "end": 3}, "(25,7903.json)": {"start": 3, "end": 3}, "(100,7760.json)": {"start": 3, "end": null}, "(5,7760.json)": {"start": 3, "end": null}, "(118,7903.json)": {"start": 3, "end": 3}, "(65,7903.json)": {"start": 3, "end": 3}, "(119,7903.json)": {"start": 3, "end": 3}, "(78,7903.json)": {"start": 3, "end": 3}, "(71,7903.json)": {"start": 3, "end": 3}, "(106,7903.json)": {"start": 3, "end": 3}, "(80,7903.json)": {"start": 3, "end": 3}, "(46,7760.json)": {"start": 3, "end": null}, "(13,7760.json)": {"start": 3, "end": null}, "(45,7903.json)": {"start": 3, "end": 3}, "(129,7903.json)": {"start": 3, "end": 3}, "(44,3930.json)": {"start": 4, "end": 4}, "(141,3930.json)": {"start": 4, "end": 4}, "(95,3930.json)": {"start": 4, "end": 4}, "(26,3930.json)": {"start": 4, "end": 4}, "(108,3930.json)": {"start": 4, "end": 4}, "(140,3930.json)": {"start": 4, "end": 4}, "(84,3930.json)": {"start": 4, "end": 4}, "(137,3930.json)": {"start": 4, "end": 4}, "(112,3930.json)": {"start": 4, "end": 4}, "(8,3930.json)": {"start": 4, "end": 4}, "(29,3930.json)": {"start": 4, "end": 4}, "(25,3930.json)": {"start": 4, "end": 4}, "(118,3930.json)": {"start": 4, "end": 4}, "(65,3930.json)": {"start": 4, "end": 4}, "(119,3930.json)": {"start": 4, "end": 4}, "(78,3930.json)": {"start": 4, "end": 4}, "(71,3930.json)": {"start": 4, "end": 4}, "(106,3930.json)": {"start": 4, "end": 4}, "(80,3930.json)": {"start": 4, "end": 4}, "(45,3930.json)": {"start": 4, "end": 4}, "(129,3930.json)": {"start": 4, "end": 4}, "(117,2003.json)": {"start": 6, "end": null}, "(92,2003.json)": {"start": 6, "end": null}, "(100,2003.json)": {"start": 6, "end": null}, "(5,2003.json)": {"start": 6, "end": null}, "(46,2003.json)": {"start": 6, "end": null}, "(13,2003.json)": {"start": 6, "end": null}, "(44,5218.json)": {"start": 12, "end": null}, "(141,5218.json)": {"start": 12, "end": null}, "(95,5218.json)": {"start": 12, "end": null}, "(26,5218.json)": {"start": 12, "end": null}, "(108,5218.json)": {"start": 12, "end": null}, "(140,5218.json)": {"start": 12, "end": null}, "(84,5218.json)": {"start": 12, "end": null}, "(137,5218.json)": {"start": 12, "end": null}, "(112,5218.json)": {"start": 12, "end": null}, "(8,5218.json)": {"start": 12, "end": null}, "(29,5218.json)": {"start": 12, "end": null}, "(25,5218.json)": {"start": 12, "end": null}, "(118,5218.json)": {"start": 12, "end": null}, "(65,5218.json)": {"start": 12, "end": null}, "(119,5218.json)": {"start": 12, "end": null}, "(78,5218.json)": {"start": 12, "end": null}, "(71,5218.json)": {"start": 12, "end": null}, "(106,5218.json)": {"start": 12, "end": null}, "(80,5218.json)": {"start": 12, "end": null}, "(45,5218.json)": {"start": 12, "end": null}, "(129,5218.json)": {"start": 12, "end": null}, "(44,1551.json)": {"start": 14, "end": 14}, "(141,1551.json)": {"start": 14, "end": 14}, "(95,1551.json)": {"start": 14, "end": 14}, "(26,1551.json)": {"start": 14, "end": 14}, "(108,1551.json)": {"start": 14, "end": 14}, "(140,1551.json)": {"start": 14, "end": 14}, "(84,1551.json)": {"start": 14, "end": 14}, "(137,1551.json)": {"start": 14, "end": 14}, "(112,1551.json)": {"start": 14, "end": 14}, "(8,1551.json)": {"start": 14, "end": 14}, "(29,1551.json)": {"start": 14, "end": 14}, "(25,1551.json)": {"start": 14, "end": 14}, "(118,1551.json)": {"start": 14, "end": 14}, "(65,1551.json)": {"start": 14, "end": 14}, "(119,1551.json)": {"start": 14, "end": 14}, "(78,1551.json)": {"start": 14, "end": 14}, "(71,1551.json)": {"start": 14, "end": 14}, "(106,1551.json)": {"start": 14, "end": 14}, "(80,1551.json)": {"start": 14, "end": 14}, "(45,1551.json)": {"start": 14, "end": 14}, "(129,1551.json)": {"start": 14, "end": 14}}