{"(86,11517.json)": {"start": 0, "end": null}, "(121,11517.json)": {"start": 0, "end": null}, "(49,11517.json)": {"start": 0, "end": null}, "(1,11517.json)": {"start": 0, "end": null}, "(130,11517.json)": {"start": 0, "end": null}, "(17,11517.json)": {"start": 0, "end": null}, "(0,11517.json)": {"start": 0, "end": null}, "(123,11517.json)": {"start": 0, "end": null}, "(10,11517.json)": {"start": 0, "end": null}, "(59,11517.json)": {"start": 0, "end": null}, "(135,11517.json)": {"start": 0, "end": null}, "(96,11517.json)": {"start": 0, "end": null}, "(91,13301.json)": {"start": 0, "end": null}, "(86,10452.json)": {"start": 3, "end": null}, "(121,10452.json)": {"start": 3, "end": null}, "(49,10452.json)": {"start": 3, "end": null}, "(1,10452.json)": {"start": 3, "end": null}, "(130,10452.json)": {"start": 3, "end": null}, "(17,10452.json)": {"start": 3, "end": null}, "(0,10452.json)": {"start": 3, "end": null}, "(123,10452.json)": {"start": 3, "end": null}, "(10,10452.json)": {"start": 3, "end": null}, "(59,10452.json)": {"start": 3, "end": null}, "(135,10452.json)": {"start": 3, "end": null}, "(96,10452.json)": {"start": 3, "end": null}, "(86,1080.json)": {"start": 4, "end": null}, "(121,1080.json)": {"start": 4, "end": null}, "(49,1080.json)": {"start": 4, "end": null}, "(1,1080.json)": {"start": 4, "end": null}, "(130,1080.json)": {"start": 4, "end": null}, "(17,1080.json)": {"start": 4, "end": null}, "(0,1080.json)": {"start": 4, "end": null}, "(123,1080.json)": {"start": 4, "end": null}, "(10,1080.json)": {"start": 4, "end": null}, "(59,1080.json)": {"start": 4, "end": null}, "(135,1080.json)": {"start": 4, "end": null}, "(96,1080.json)": {"start": 4, "end": null}, "(86,5977.json)": {"start": 6, "end": null}, "(121,5977.json)": {"start": 6, "end": null}, "(49,5977.json)": {"start": 6, "end": null}, "(1,5977.json)": {"start": 6, "end": null}, "(130,5977.json)": {"start": 6, "end": null}, "(17,5977.json)": {"start": 6, "end": null}, "(0,5977.json)": {"start": 6, "end": null}, "(123,5977.json)": {"start": 6, "end": null}, "(10,5977.json)": {"start": 6, "end": null}, "(59,5977.json)": {"start": 6, "end": null}, "(135,5977.json)": {"start": 6, "end": null}, "(96,5977.json)": {"start": 6, "end": null}, "(91,9347.json)": {"start": 6, "end": 6}, "(86,1167.json)": {"start": 10, "end": null}, "(121,1167.json)": {"start": 10, "end": null}, "(49,1167.json)": {"start": 10, "end": null}, "(1,1167.json)": {"start": 10, "end": null}, "(130,1167.json)": {"start": 10, "end": null}, "(17,1167.json)": {"start": 10, "end": null}, "(0,1167.json)": {"start": 10, "end": null}, "(123,1167.json)": {"start": 10, "end": null}, "(10,1167.json)": {"start": 10, "end": null}, "(59,1167.json)": {"start": 10, "end": null}, "(135,1167.json)": {"start": 10, "end": null}, "(96,1167.json)": {"start": 10, "end": null}, "(91,12844.json)": {"start": 10, "end": null}, "(91,1597.json)": {"start": 11, "end": null}, "(86,2516.json)": {"start": 13, "end": 13}, "(121,2516.json)": {"start": 13, "end": 13}, "(49,2516.json)": {"start": 13, "end": 13}, "(1,2516.json)": {"start": 13, "end": 13}, "(130,2516.json)": {"start": 13, "end": 13}, "(17,2516.json)": {"start": 13, "end": 13}, "(0,2516.json)": {"start": 13, "end": 13}, "(123,2516.json)": {"start": 13, "end": 13}, "(10,2516.json)": {"start": 13, "end": 13}, "(59,2516.json)": {"start": 13, "end": 13}, "(135,2516.json)": {"start": 13, "end": 13}, "(96,2516.json)": {"start": 13, "end": 13}}