{"32": {"start": 0, "end": 9}, "54": {"start": 0, "end": 9}, "96": {"start": 0, "end": 9}, "117": {"start": 0, "end": 9}, "136": {"start": 0, "end": null}, "110": {"start": 0, "end": 9}, "8": {"start": 0, "end": 9}, "119": {"start": 0, "end": 9}, "45": {"start": 0, "end": 9}, "56": {"start": 0, "end": null}, "5": {"start": 0, "end": 9}, "50": {"start": 0, "end": 9}, "1": {"start": 0, "end": null}, "142": {"start": 0, "end": 9}, "103": {"start": 0, "end": 9}, "71": {"start": 0, "end": 9}, "139": {"start": 0, "end": 9}, "40": {"start": 0, "end": 9}, "122": {"start": 0, "end": 9}, "68": {"start": 0, "end": 9}, "123": {"start": 0, "end": 9}, "69": {"start": 0, "end": 9}, "94": {"start": 0, "end": 9}, "91": {"start": 0, "end": null}, "48": {"start": 0, "end": 9}, "126": {"start": 0, "end": 9}, "13": {"start": 0, "end": 9}}