{"24": {"start": 0, "end": 7}, "3": {"start": 0, "end": 7}, "123": {"start": 0, "end": 7}, "131": {"start": 0, "end": 7}, "10": {"start": 0, "end": 7}, "108": {"start": 1, "end": 5}, "114": {"start": 1, "end": 5}, "33": {"start": 1, "end": 5}, "71": {"start": 1, "end": 5}, "129": {"start": 1, "end": 5}, "112": {"start": 1, "end": 5}, "28": {"start": 1, "end": 5}, "66": {"start": 1, "end": 5}, "122": {"start": 1, "end": 5}, "68": {"start": 1, "end": 5}, "44": {"start": 1, "end": 5}, "121": {"start": 1, "end": 5}, "92": {"start": 1, "end": 5}, "85": {"start": 1, "end": 5}, "23": {"start": 1, "end": 5}, "107": {"start": 1, "end": 5}, "64": {"start": 1, "end": 5}, "135": {"start": 1, "end": 5}, "36": {"start": 1, "end": 5}, "77": {"start": 1, "end": 5}, "65": {"start": 1, "end": 5}, "8": {"start": 1, "end": 5}}