{"(14,7539.json)": {"start": 0, "end": 0}, "(16,7539.json)": {"start": 0, "end": 0}, "(48,7539.json)": {"start": 0, "end": 0}, "(88,7539.json)": {"start": 0, "end": 0}, "(136,7539.json)": {"start": 0, "end": 0}, "(47,7539.json)": {"start": 0, "end": 0}, "(138,7539.json)": {"start": 0, "end": 0}, "(23,3918.json)": {"start": 0, "end": 0}, "(113,3918.json)": {"start": 0, "end": 0}, "(99,7539.json)": {"start": 0, "end": 0}, "(107,3918.json)": {"start": 0, "end": 0}, "(11,7539.json)": {"start": 0, "end": 0}, "(124,3918.json)": {"start": 0, "end": 0}, "(57,7539.json)": {"start": 0, "end": 0}, "(24,3918.json)": {"start": 0, "end": 0}, "(51,7539.json)": {"start": 0, "end": 0}, "(28,7539.json)": {"start": 0, "end": 0}, "(91,7539.json)": {"start": 0, "end": 0}, "(81,7539.json)": {"start": 0, "end": 0}, "(35,7539.json)": {"start": 0, "end": 0}, "(142,7539.json)": {"start": 0, "end": 0}, "(46,3918.json)": {"start": 0, "end": 0}, "(7,7539.json)": {"start": 0, "end": 0}, "(82,3918.json)": {"start": 0, "end": 0}, "(92,7539.json)": {"start": 0, "end": 0}, "(141,3918.json)": {"start": 0, "end": 0}, "(139,7539.json)": {"start": 0, "end": 0}, "(23,7501.json)": {"start": 1, "end": 1}, "(113,7501.json)": {"start": 1, "end": 1}, "(107,7501.json)": {"start": 1, "end": 1}, "(124,7501.json)": {"start": 1, "end": 1}, "(24,7501.json)": {"start": 1, "end": 1}, "(46,7501.json)": {"start": 1, "end": 1}, "(82,7501.json)": {"start": 1, "end": 1}, "(141,7501.json)": {"start": 1, "end": 1}, "(23,11622.json)": {"start": 2, "end": 2}, "(113,11622.json)": {"start": 2, "end": 2}, "(107,11622.json)": {"start": 2, "end": 2}, "(124,11622.json)": {"start": 2, "end": 2}, "(24,11622.json)": {"start": 2, "end": 2}, "(46,11622.json)": {"start": 2, "end": 2}, "(82,11622.json)": {"start": 2, "end": 2}, "(141,11622.json)": {"start": 2, "end": 2}, "(23,10979.json)": {"start": 3, "end": 3}, "(113,10979.json)": {"start": 3, "end": 3}, "(107,10979.json)": {"start": 3, "end": 3}, "(124,10979.json)": {"start": 3, "end": 3}, "(24,10979.json)": {"start": 3, "end": 3}, "(46,10979.json)": {"start": 3, "end": 3}, "(82,10979.json)": {"start": 3, "end": 3}, "(141,10979.json)": {"start": 3, "end": 3}, "(23,6237.json)": {"start": 5, "end": 5}, "(113,6237.json)": {"start": 5, "end": 5}, "(107,6237.json)": {"start": 5, "end": 5}, "(124,6237.json)": {"start": 5, "end": 5}, "(24,6237.json)": {"start": 5, "end": 5}, "(46,6237.json)": {"start": 5, "end": 5}, "(82,6237.json)": {"start": 5, "end": 5}, "(141,6237.json)": {"start": 5, "end": 5}, "(14,2938.json)": {"start": 6, "end": 6}, "(16,2938.json)": {"start": 6, "end": 6}, "(48,2938.json)": {"start": 6, "end": 6}, "(88,2938.json)": {"start": 6, "end": 6}, "(136,2938.json)": {"start": 6, "end": 6}, "(47,2938.json)": {"start": 6, "end": 6}, "(138,2938.json)": {"start": 6, "end": 6}, "(99,2938.json)": {"start": 6, "end": 6}, "(11,2938.json)": {"start": 6, "end": 6}, "(57,2938.json)": {"start": 6, "end": 6}, "(51,2938.json)": {"start": 6, "end": 6}, "(28,2938.json)": {"start": 6, "end": 6}, "(91,2938.json)": {"start": 6, "end": 6}, "(81,2938.json)": {"start": 6, "end": 6}, "(35,2938.json)": {"start": 6, "end": 6}, "(142,2938.json)": {"start": 6, "end": 6}, "(7,2938.json)": {"start": 6, "end": 6}, "(92,2938.json)": {"start": 6, "end": 6}, "(139,2938.json)": {"start": 6, "end": 6}, "(23,10649.json)": {"start": 7, "end": 7}, "(113,10649.json)": {"start": 7, "end": 7}, "(107,10649.json)": {"start": 7, "end": 7}, "(124,10649.json)": {"start": 7, "end": 7}, "(24,10649.json)": {"start": 7, "end": 7}, "(46,10649.json)": {"start": 7, "end": 7}, "(82,10649.json)": {"start": 7, "end": 7}, "(141,10649.json)": {"start": 7, "end": 7}, "(14,8644.json)": {"start": 12, "end": 12}, "(16,8644.json)": {"start": 12, "end": 12}, "(48,8644.json)": {"start": 12, "end": 12}, "(88,8644.json)": {"start": 12, "end": 12}, "(136,8644.json)": {"start": 12, "end": 12}, "(47,8644.json)": {"start": 12, "end": 12}, "(138,8644.json)": {"start": 12, "end": 12}, "(99,8644.json)": {"start": 12, "end": 12}, "(11,8644.json)": {"start": 12, "end": 12}, "(57,8644.json)": {"start": 12, "end": 12}, "(51,8644.json)": {"start": 12, "end": 12}, "(28,8644.json)": {"start": 12, "end": 12}, "(91,8644.json)": {"start": 12, "end": 12}, "(81,8644.json)": {"start": 12, "end": 12}, "(35,8644.json)": {"start": 12, "end": 12}, "(142,8644.json)": {"start": 12, "end": 12}, "(7,8644.json)": {"start": 12, "end": 12}, "(92,8644.json)": {"start": 12, "end": 12}, "(139,8644.json)": {"start": 12, "end": 12}, "(23,6717.json)": {"start": 13, "end": 13}, "(113,6717.json)": {"start": 13, "end": 13}, "(107,6717.json)": {"start": 13, "end": 13}, "(124,6717.json)": {"start": 13, "end": 13}, "(24,6717.json)": {"start": 13, "end": 13}, "(46,6717.json)": {"start": 13, "end": 13}, "(82,6717.json)": {"start": 13, "end": 13}, "(141,6717.json)": {"start": 13, "end": 13}}