{"(136,7566.json)": {"start": 6, "end": 6}, "(91,4602.json)": {"start": 6, "end": null}, "(119,4602.json)": {"start": 6, "end": null}, "(127,4602.json)": {"start": 6, "end": null}, "(132,4602.json)": {"start": 6, "end": null}, "(34,7566.json)": {"start": 6, "end": 6}, "(25,4602.json)": {"start": 6, "end": null}, "(7,4602.json)": {"start": 6, "end": null}, "(126,4602.json)": {"start": 6, "end": null}, "(46,4602.json)": {"start": 6, "end": null}, "(142,4602.json)": {"start": 6, "end": null}, "(69,4602.json)": {"start": 6, "end": null}, "(73,4602.json)": {"start": 6, "end": null}, "(1,4602.json)": {"start": 6, "end": null}, "(87,4602.json)": {"start": 6, "end": null}, "(23,4602.json)": {"start": 6, "end": null}, "(118,7566.json)": {"start": 6, "end": 6}, "(58,4602.json)": {"start": 6, "end": null}, "(107,4602.json)": {"start": 6, "end": null}, "(103,4602.json)": {"start": 6, "end": null}, "(26,4602.json)": {"start": 6, "end": null}, "(3,4602.json)": {"start": 6, "end": null}, "(128,4602.json)": {"start": 6, "end": null}, "(75,7566.json)": {"start": 6, "end": 6}, "(40,4602.json)": {"start": 6, "end": null}, "(12,4602.json)": {"start": 6, "end": null}, "(95,4602.json)": {"start": 6, "end": null}, "(136,5666.json)": {"start": 8, "end": 8}, "(34,5666.json)": {"start": 8, "end": 8}, "(118,5666.json)": {"start": 8, "end": 8}, "(75,5666.json)": {"start": 8, "end": 8}, "(136,10485.json)": {"start": 9, "end": null}, "(91,7398.json)": {"start": 9, "end": null}, "(119,7398.json)": {"start": 9, "end": null}, "(127,7398.json)": {"start": 9, "end": null}, "(132,7398.json)": {"start": 9, "end": null}, "(34,10485.json)": {"start": 9, "end": null}, "(25,7398.json)": {"start": 9, "end": null}, "(7,7398.json)": {"start": 9, "end": null}, "(126,7398.json)": {"start": 9, "end": null}, "(46,7398.json)": {"start": 9, "end": null}, "(142,7398.json)": {"start": 9, "end": null}, "(69,7398.json)": {"start": 9, "end": null}, "(73,7398.json)": {"start": 9, "end": null}, "(1,7398.json)": {"start": 9, "end": null}, "(87,7398.json)": {"start": 9, "end": null}, "(23,7398.json)": {"start": 9, "end": null}, "(118,10485.json)": {"start": 9, "end": null}, "(58,7398.json)": {"start": 9, "end": null}, "(107,7398.json)": {"start": 9, "end": null}, "(103,7398.json)": {"start": 9, "end": null}, "(26,7398.json)": {"start": 9, "end": null}, "(3,7398.json)": {"start": 9, "end": null}, "(128,7398.json)": {"start": 9, "end": null}, "(75,10485.json)": {"start": 9, "end": null}, "(40,7398.json)": {"start": 9, "end": null}, "(12,7398.json)": {"start": 9, "end": null}, "(95,7398.json)": {"start": 9, "end": null}, "(91,3670.json)": {"start": 10, "end": null}, "(119,3670.json)": {"start": 10, "end": null}, "(127,3670.json)": {"start": 10, "end": null}, "(132,3670.json)": {"start": 10, "end": null}, "(25,3670.json)": {"start": 10, "end": null}, "(7,3670.json)": {"start": 10, "end": null}, "(126,3670.json)": {"start": 10, "end": null}, "(46,3670.json)": {"start": 10, "end": null}, "(142,3670.json)": {"start": 10, "end": null}, "(69,3670.json)": {"start": 10, "end": null}, "(73,3670.json)": {"start": 10, "end": null}, "(1,3670.json)": {"start": 10, "end": null}, "(87,3670.json)": {"start": 10, "end": null}, "(23,3670.json)": {"start": 10, "end": null}, "(58,3670.json)": {"start": 10, "end": null}, "(107,3670.json)": {"start": 10, "end": null}, "(103,3670.json)": {"start": 10, "end": null}, "(26,3670.json)": {"start": 10, "end": null}, "(3,3670.json)": {"start": 10, "end": null}, "(128,3670.json)": {"start": 10, "end": null}, "(40,3670.json)": {"start": 10, "end": null}, "(12,3670.json)": {"start": 10, "end": null}, "(95,3670.json)": {"start": 10, "end": null}, "(91,4732.json)": {"start": 11, "end": 12}, "(119,4732.json)": {"start": 11, "end": 12}, "(127,4732.json)": {"start": 11, "end": 12}, "(132,4732.json)": {"start": 11, "end": 12}, "(25,4732.json)": {"start": 11, "end": 12}, "(7,4732.json)": {"start": 11, "end": 12}, "(126,4732.json)": {"start": 11, "end": 12}, "(46,4732.json)": {"start": 11, "end": 12}, "(142,4732.json)": {"start": 11, "end": 12}, "(69,4732.json)": {"start": 11, "end": 12}, "(73,4732.json)": {"start": 11, "end": 12}, "(1,4732.json)": {"start": 11, "end": 12}, "(87,4732.json)": {"start": 11, "end": 12}, "(23,4732.json)": {"start": 11, "end": 12}, "(58,4732.json)": {"start": 11, "end": 12}, "(107,4732.json)": {"start": 11, "end": 12}, "(103,4732.json)": {"start": 11, "end": 12}, "(26,4732.json)": {"start": 11, "end": 12}, "(3,4732.json)": {"start": 11, "end": 12}, "(128,4732.json)": {"start": 11, "end": 12}, "(40,4732.json)": {"start": 11, "end": 12}, "(12,4732.json)": {"start": 11, "end": 12}, "(95,4732.json)": {"start": 11, "end": 12}, "(136,13388.json)": {"start": 12, "end": null}, "(34,13388.json)": {"start": 12, "end": null}, "(118,13388.json)": {"start": 12, "end": null}, "(75,13388.json)": {"start": 12, "end": null}, "(91,5235.json)": {"start": 13, "end": 14}, "(119,5235.json)": {"start": 13, "end": 14}, "(127,5235.json)": {"start": 13, "end": 14}, "(132,5235.json)": {"start": 13, "end": 14}, "(25,5235.json)": {"start": 13, "end": 14}, "(7,5235.json)": {"start": 13, "end": 14}, "(126,5235.json)": {"start": 13, "end": 14}, "(46,5235.json)": {"start": 13, "end": 14}, "(142,5235.json)": {"start": 13, "end": 14}, "(69,5235.json)": {"start": 13, "end": 14}, "(73,5235.json)": {"start": 13, "end": 14}, "(1,5235.json)": {"start": 13, "end": 14}, "(87,5235.json)": {"start": 13, "end": 14}, "(23,5235.json)": {"start": 13, "end": 14}, "(58,5235.json)": {"start": 13, "end": 14}, "(107,5235.json)": {"start": 13, "end": 14}, "(103,5235.json)": {"start": 13, "end": 14}, "(26,5235.json)": {"start": 13, "end": 14}, "(3,5235.json)": {"start": 13, "end": 14}, "(128,5235.json)": {"start": 13, "end": 14}, "(40,5235.json)": {"start": 13, "end": 14}, "(12,5235.json)": {"start": 13, "end": 14}, "(95,5235.json)": {"start": 13, "end": 14}, "(136,13037.json)": {"start": 14, "end": null}, "(34,13037.json)": {"start": 14, "end": null}, "(118,13037.json)": {"start": 14, "end": null}, "(75,13037.json)": {"start": 14, "end": null}}