{"(95,11136.json)": {"start": 1, "end": 1}, "(16,11136.json)": {"start": 1, "end": 1}, "(148,11136.json)": {"start": 1, "end": 1}, "(39,11136.json)": {"start": 1, "end": 1}, "(20,11136.json)": {"start": 1, "end": 1}, "(85,11136.json)": {"start": 1, "end": 1}, "(17,11136.json)": {"start": 1, "end": 1}, "(98,11136.json)": {"start": 1, "end": 1}, "(42,11136.json)": {"start": 1, "end": 1}, "(126,11136.json)": {"start": 1, "end": 1}, "(38,11136.json)": {"start": 1, "end": 1}, "(18,11136.json)": {"start": 1, "end": 1}, "(125,11136.json)": {"start": 1, "end": 1}, "(29,11136.json)": {"start": 1, "end": 1}, "(26,11136.json)": {"start": 1, "end": 1}, "(82,11136.json)": {"start": 1, "end": 1}, "(68,11136.json)": {"start": 1, "end": 1}, "(135,11136.json)": {"start": 1, "end": 1}, "(45,11136.json)": {"start": 1, "end": 1}, "(2,11136.json)": {"start": 1, "end": 1}, "(54,12442.json)": {"start": 2, "end": null}, "(33,12442.json)": {"start": 2, "end": null}, "(103,12442.json)": {"start": 2, "end": null}, "(84,12442.json)": {"start": 2, "end": null}, "(36,12442.json)": {"start": 2, "end": null}, "(32,12442.json)": {"start": 2, "end": null}, "(88,12442.json)": {"start": 2, "end": null}, "(95,7754.json)": {"start": 3, "end": null}, "(16,7754.json)": {"start": 3, "end": null}, "(148,7754.json)": {"start": 3, "end": null}, "(39,7754.json)": {"start": 3, "end": null}, "(20,7754.json)": {"start": 3, "end": null}, "(85,7754.json)": {"start": 3, "end": null}, "(17,7754.json)": {"start": 3, "end": null}, "(98,7754.json)": {"start": 3, "end": null}, "(42,7754.json)": {"start": 3, "end": null}, "(126,7754.json)": {"start": 3, "end": null}, "(38,7754.json)": {"start": 3, "end": null}, "(18,7754.json)": {"start": 3, "end": null}, "(125,7754.json)": {"start": 3, "end": null}, "(29,7754.json)": {"start": 3, "end": null}, "(26,7754.json)": {"start": 3, "end": null}, "(82,7754.json)": {"start": 3, "end": null}, "(68,7754.json)": {"start": 3, "end": null}, "(135,7754.json)": {"start": 3, "end": null}, "(45,7754.json)": {"start": 3, "end": null}, "(2,7754.json)": {"start": 3, "end": null}, "(95,3256.json)": {"start": 5, "end": 5}, "(16,3256.json)": {"start": 5, "end": 5}, "(148,3256.json)": {"start": 5, "end": 5}, "(39,3256.json)": {"start": 5, "end": 5}, "(20,3256.json)": {"start": 5, "end": 5}, "(85,3256.json)": {"start": 5, "end": 5}, "(17,3256.json)": {"start": 5, "end": 5}, "(98,3256.json)": {"start": 5, "end": 5}, "(42,3256.json)": {"start": 5, "end": 5}, "(126,3256.json)": {"start": 5, "end": 5}, "(38,3256.json)": {"start": 5, "end": 5}, "(18,3256.json)": {"start": 5, "end": 5}, "(125,3256.json)": {"start": 5, "end": 5}, "(29,3256.json)": {"start": 5, "end": 5}, "(26,3256.json)": {"start": 5, "end": 5}, "(82,3256.json)": {"start": 5, "end": 5}, "(68,3256.json)": {"start": 5, "end": 5}, "(135,3256.json)": {"start": 5, "end": 5}, "(45,3256.json)": {"start": 5, "end": 5}, "(2,3256.json)": {"start": 5, "end": 5}, "(54,5377.json)": {"start": 6, "end": 7}, "(33,5377.json)": {"start": 6, "end": 7}, "(103,5377.json)": {"start": 6, "end": 7}, "(84,5377.json)": {"start": 6, "end": 7}, "(36,5377.json)": {"start": 6, "end": 7}, "(32,5377.json)": {"start": 6, "end": 7}, "(88,5377.json)": {"start": 6, "end": 7}, "(54,3340.json)": {"start": 10, "end": null}, "(95,6217.json)": {"start": 10, "end": 10}, "(16,6217.json)": {"start": 10, "end": 10}, "(148,6217.json)": {"start": 10, "end": 10}, "(39,6217.json)": {"start": 10, "end": 10}, "(20,6217.json)": {"start": 10, "end": 10}, "(85,6217.json)": {"start": 10, "end": 10}, "(17,6217.json)": {"start": 10, "end": 10}, "(98,6217.json)": {"start": 10, "end": 10}, "(42,6217.json)": {"start": 10, "end": 10}, "(33,3340.json)": {"start": 10, "end": null}, "(126,6217.json)": {"start": 10, "end": 10}, "(38,6217.json)": {"start": 10, "end": 10}, "(18,6217.json)": {"start": 10, "end": 10}, "(125,6217.json)": {"start": 10, "end": 10}, "(29,6217.json)": {"start": 10, "end": 10}, "(26,6217.json)": {"start": 10, "end": 10}, "(82,6217.json)": {"start": 10, "end": 10}, "(103,3340.json)": {"start": 10, "end": null}, "(84,3340.json)": {"start": 10, "end": null}, "(36,3340.json)": {"start": 10, "end": null}, "(68,6217.json)": {"start": 10, "end": 10}, "(32,3340.json)": {"start": 10, "end": null}, "(135,6217.json)": {"start": 10, "end": 10}, "(45,6217.json)": {"start": 10, "end": 10}, "(2,6217.json)": {"start": 10, "end": 10}, "(88,3340.json)": {"start": 10, "end": null}, "(54,8138.json)": {"start": 11, "end": null}, "(33,8138.json)": {"start": 11, "end": null}, "(103,8138.json)": {"start": 11, "end": null}, "(84,8138.json)": {"start": 11, "end": null}, "(36,8138.json)": {"start": 11, "end": null}, "(32,8138.json)": {"start": 11, "end": null}, "(88,8138.json)": {"start": 11, "end": null}, "(54,13178.json)": {"start": 12, "end": null}, "(95,4274.json)": {"start": 12, "end": null}, "(16,4274.json)": {"start": 12, "end": null}, "(148,4274.json)": {"start": 12, "end": null}, "(39,4274.json)": {"start": 12, "end": null}, "(20,4274.json)": {"start": 12, "end": null}, "(85,4274.json)": {"start": 12, "end": null}, "(17,4274.json)": {"start": 12, "end": null}, "(98,4274.json)": {"start": 12, "end": null}, "(42,4274.json)": {"start": 12, "end": null}, "(33,13178.json)": {"start": 12, "end": null}, "(126,4274.json)": {"start": 12, "end": null}, "(38,4274.json)": {"start": 12, "end": null}, "(18,4274.json)": {"start": 12, "end": null}, "(125,4274.json)": {"start": 12, "end": null}, "(29,4274.json)": {"start": 12, "end": null}, "(26,4274.json)": {"start": 12, "end": null}, "(82,4274.json)": {"start": 12, "end": null}, "(103,13178.json)": {"start": 12, "end": null}, "(84,13178.json)": {"start": 12, "end": null}, "(36,13178.json)": {"start": 12, "end": null}, "(68,4274.json)": {"start": 12, "end": null}, "(32,13178.json)": {"start": 12, "end": null}, "(135,4274.json)": {"start": 12, "end": null}, "(45,4274.json)": {"start": 12, "end": null}, "(2,4274.json)": {"start": 12, "end": null}, "(88,13178.json)": {"start": 12, "end": null}, "(54,11197.json)": {"start": 13, "end": 14}, "(33,11197.json)": {"start": 13, "end": 14}, "(103,11197.json)": {"start": 13, "end": 14}, "(84,11197.json)": {"start": 13, "end": 14}, "(36,11197.json)": {"start": 13, "end": 14}, "(32,11197.json)": {"start": 13, "end": 14}, "(88,11197.json)": {"start": 13, "end": 14}}