{"(27,11136.json)": {"start": 1, "end": 1}, "(141,11136.json)": {"start": 1, "end": 1}, "(46,11136.json)": {"start": 1, "end": 1}, "(83,11136.json)": {"start": 1, "end": 1}, "(129,11136.json)": {"start": 1, "end": 1}, "(22,11136.json)": {"start": 1, "end": 1}, "(38,11136.json)": {"start": 1, "end": 1}, "(12,11136.json)": {"start": 1, "end": 1}, "(13,11136.json)": {"start": 1, "end": 1}, "(33,11136.json)": {"start": 1, "end": 1}, "(40,11136.json)": {"start": 1, "end": 1}, "(105,11136.json)": {"start": 1, "end": 1}, "(18,11136.json)": {"start": 1, "end": 1}, "(58,11136.json)": {"start": 1, "end": 1}, "(7,11136.json)": {"start": 1, "end": 1}, "(21,11136.json)": {"start": 1, "end": 1}, "(119,11136.json)": {"start": 1, "end": 1}, "(75,11136.json)": {"start": 1, "end": 1}, "(66,11136.json)": {"start": 1, "end": 1}, "(64,4395.json)": {"start": 2, "end": 2}, "(114,4395.json)": {"start": 2, "end": 2}, "(124,4395.json)": {"start": 2, "end": 2}, "(118,4395.json)": {"start": 2, "end": 2}, "(133,4395.json)": {"start": 2, "end": 2}, "(61,4395.json)": {"start": 2, "end": 2}, "(106,4395.json)": {"start": 2, "end": 2}, "(73,4395.json)": {"start": 2, "end": 2}, "(27,7754.json)": {"start": 3, "end": 3}, "(141,7754.json)": {"start": 3, "end": 3}, "(46,7754.json)": {"start": 3, "end": 3}, "(83,7754.json)": {"start": 3, "end": 3}, "(129,7754.json)": {"start": 3, "end": 3}, "(22,7754.json)": {"start": 3, "end": 3}, "(38,7754.json)": {"start": 3, "end": 3}, "(12,7754.json)": {"start": 3, "end": 3}, "(13,7754.json)": {"start": 3, "end": 3}, "(33,7754.json)": {"start": 3, "end": 3}, "(40,7754.json)": {"start": 3, "end": 3}, "(105,7754.json)": {"start": 3, "end": 3}, "(18,7754.json)": {"start": 3, "end": 3}, "(58,7754.json)": {"start": 3, "end": 3}, "(7,7754.json)": {"start": 3, "end": 3}, "(21,7754.json)": {"start": 3, "end": 3}, "(119,7754.json)": {"start": 3, "end": 3}, "(75,7754.json)": {"start": 3, "end": 3}, "(66,7754.json)": {"start": 3, "end": 3}, "(64,8624.json)": {"start": 4, "end": 4}, "(114,8624.json)": {"start": 4, "end": 4}, "(124,8624.json)": {"start": 4, "end": 4}, "(118,8624.json)": {"start": 4, "end": 4}, "(133,8624.json)": {"start": 4, "end": 4}, "(61,8624.json)": {"start": 4, "end": 4}, "(106,8624.json)": {"start": 4, "end": 4}, "(73,8624.json)": {"start": 4, "end": 4}, "(27,3256.json)": {"start": 5, "end": 5}, "(141,3256.json)": {"start": 5, "end": 5}, "(46,3256.json)": {"start": 5, "end": 5}, "(83,3256.json)": {"start": 5, "end": 5}, "(129,3256.json)": {"start": 5, "end": 5}, "(22,3256.json)": {"start": 5, "end": 5}, "(38,3256.json)": {"start": 5, "end": 5}, "(12,3256.json)": {"start": 5, "end": 5}, "(13,3256.json)": {"start": 5, "end": 5}, "(33,3256.json)": {"start": 5, "end": 5}, "(40,3256.json)": {"start": 5, "end": 5}, "(105,3256.json)": {"start": 5, "end": 5}, "(18,3256.json)": {"start": 5, "end": 5}, "(58,3256.json)": {"start": 5, "end": 5}, "(7,3256.json)": {"start": 5, "end": 5}, "(21,3256.json)": {"start": 5, "end": 5}, "(119,3256.json)": {"start": 5, "end": 5}, "(75,3256.json)": {"start": 5, "end": 5}, "(66,3256.json)": {"start": 5, "end": 5}, "(27,6217.json)": {"start": 10, "end": 10}, "(141,6217.json)": {"start": 10, "end": 10}, "(46,6217.json)": {"start": 10, "end": 10}, "(83,6217.json)": {"start": 10, "end": 10}, "(129,6217.json)": {"start": 10, "end": 10}, "(22,6217.json)": {"start": 10, "end": 10}, "(38,6217.json)": {"start": 10, "end": 10}, "(12,6217.json)": {"start": 10, "end": 10}, "(13,6217.json)": {"start": 10, "end": 10}, "(33,6217.json)": {"start": 10, "end": 10}, "(40,6217.json)": {"start": 10, "end": 10}, "(105,6217.json)": {"start": 10, "end": 10}, "(18,6217.json)": {"start": 10, "end": 10}, "(58,6217.json)": {"start": 10, "end": 10}, "(7,6217.json)": {"start": 10, "end": 10}, "(21,6217.json)": {"start": 10, "end": 10}, "(119,6217.json)": {"start": 10, "end": 10}, "(75,6217.json)": {"start": 10, "end": 10}, "(66,6217.json)": {"start": 10, "end": 10}, "(27,4274.json)": {"start": 12, "end": 12}, "(141,4274.json)": {"start": 12, "end": 12}, "(46,4274.json)": {"start": 12, "end": 12}, "(83,4274.json)": {"start": 12, "end": 12}, "(129,4274.json)": {"start": 12, "end": 12}, "(22,4274.json)": {"start": 12, "end": 12}, "(38,4274.json)": {"start": 12, "end": 12}, "(12,4274.json)": {"start": 12, "end": 12}, "(13,4274.json)": {"start": 12, "end": 12}, "(33,4274.json)": {"start": 12, "end": 12}, "(40,4274.json)": {"start": 12, "end": 12}, "(105,4274.json)": {"start": 12, "end": 12}, "(18,4274.json)": {"start": 12, "end": 12}, "(58,4274.json)": {"start": 12, "end": 12}, "(7,4274.json)": {"start": 12, "end": 12}, "(21,4274.json)": {"start": 12, "end": 12}, "(119,4274.json)": {"start": 12, "end": 12}, "(75,4274.json)": {"start": 12, "end": 12}, "(66,4274.json)": {"start": 12, "end": 12}}