{"56": {"start": 0, "end": 0}, "140": {"start": 0, "end": 0}, "52": {"start": 0, "end": 0}, "88": {"start": 0, "end": 0}, "63": {"start": 0, "end": 0}, "59": {"start": 0, "end": 0}, "21": {"start": 0, "end": 0}, "6": {"start": 0, "end": 0}, "75": {"start": 1, "end": 12}, "38": {"start": 1, "end": 12}, "0": {"start": 1, "end": 12}, "28": {"start": 1, "end": 12}, "33": {"start": 1, "end": 12}, "123": {"start": 1, "end": 12}, "145": {"start": 1, "end": 12}, "60": {"start": 1, "end": 12}, "43": {"start": 1, "end": 12}, "1": {"start": 1, "end": 12}, "147": {"start": 1, "end": 12}, "51": {"start": 1, "end": 12}, "78": {"start": 1, "end": 12}, "98": {"start": 1, "end": 12}, "67": {"start": 1, "end": 12}, "87": {"start": 1, "end": 12}, "32": {"start": 1, "end": 12}, "44": {"start": 1, "end": 12}, "20": {"start": 1, "end": 12}}