{"(99,4602.json)": {"start": 6, "end": null}, "(78,271.json)": {"start": 6, "end": null}, "(21,271.json)": {"start": 6, "end": null}, "(46,4602.json)": {"start": 6, "end": null}, "(5,4602.json)": {"start": 6, "end": null}, "(107,4602.json)": {"start": 6, "end": null}, "(22,4602.json)": {"start": 6, "end": null}, "(16,271.json)": {"start": 6, "end": null}, "(29,4602.json)": {"start": 6, "end": null}, "(35,4602.json)": {"start": 6, "end": null}, "(116,4602.json)": {"start": 6, "end": null}, "(65,4602.json)": {"start": 6, "end": null}, "(92,271.json)": {"start": 6, "end": null}, "(110,4602.json)": {"start": 6, "end": null}, "(94,4602.json)": {"start": 6, "end": null}, "(105,4602.json)": {"start": 6, "end": null}, "(14,271.json)": {"start": 6, "end": null}, "(124,4602.json)": {"start": 6, "end": null}, "(128,4602.json)": {"start": 6, "end": null}, "(56,4602.json)": {"start": 6, "end": null}, "(1,271.json)": {"start": 6, "end": null}, "(119,4602.json)": {"start": 6, "end": null}, "(133,4602.json)": {"start": 6, "end": null}, "(66,4602.json)": {"start": 6, "end": null}, "(91,271.json)": {"start": 6, "end": null}, "(136,4602.json)": {"start": 6, "end": null}, "(4,4602.json)": {"start": 6, "end": null}, "(99,7398.json)": {"start": 9, "end": null}, "(78,12165.json)": {"start": 9, "end": null}, "(21,12165.json)": {"start": 9, "end": null}, "(46,7398.json)": {"start": 9, "end": null}, "(5,7398.json)": {"start": 9, "end": null}, "(107,7398.json)": {"start": 9, "end": null}, "(22,7398.json)": {"start": 9, "end": null}, "(16,12165.json)": {"start": 9, "end": null}, "(29,7398.json)": {"start": 9, "end": null}, "(35,7398.json)": {"start": 9, "end": null}, "(116,7398.json)": {"start": 9, "end": null}, "(65,7398.json)": {"start": 9, "end": null}, "(92,12165.json)": {"start": 9, "end": null}, "(110,7398.json)": {"start": 9, "end": null}, "(94,7398.json)": {"start": 9, "end": null}, "(105,7398.json)": {"start": 9, "end": null}, "(14,12165.json)": {"start": 9, "end": null}, "(124,7398.json)": {"start": 9, "end": null}, "(128,7398.json)": {"start": 9, "end": null}, "(56,7398.json)": {"start": 9, "end": null}, "(1,12165.json)": {"start": 9, "end": null}, "(119,7398.json)": {"start": 9, "end": null}, "(133,7398.json)": {"start": 9, "end": null}, "(66,7398.json)": {"start": 9, "end": null}, "(91,12165.json)": {"start": 9, "end": null}, "(136,7398.json)": {"start": 9, "end": null}, "(4,7398.json)": {"start": 9, "end": null}, "(99,3670.json)": {"start": 10, "end": null}, "(78,8019.json)": {"start": 10, "end": 10}, "(21,8019.json)": {"start": 10, "end": 10}, "(46,3670.json)": {"start": 10, "end": null}, "(5,3670.json)": {"start": 10, "end": null}, "(107,3670.json)": {"start": 10, "end": null}, "(22,3670.json)": {"start": 10, "end": null}, "(16,8019.json)": {"start": 10, "end": 10}, "(29,3670.json)": {"start": 10, "end": null}, "(35,3670.json)": {"start": 10, "end": null}, "(116,3670.json)": {"start": 10, "end": null}, "(65,3670.json)": {"start": 10, "end": null}, "(92,8019.json)": {"start": 10, "end": 10}, "(110,3670.json)": {"start": 10, "end": null}, "(94,3670.json)": {"start": 10, "end": null}, "(105,3670.json)": {"start": 10, "end": null}, "(14,8019.json)": {"start": 10, "end": 10}, "(124,3670.json)": {"start": 10, "end": null}, "(128,3670.json)": {"start": 10, "end": null}, "(56,3670.json)": {"start": 10, "end": null}, "(1,8019.json)": {"start": 10, "end": 10}, "(119,3670.json)": {"start": 10, "end": null}, "(133,3670.json)": {"start": 10, "end": null}, "(66,3670.json)": {"start": 10, "end": null}, "(91,8019.json)": {"start": 10, "end": 10}, "(136,3670.json)": {"start": 10, "end": null}, "(4,3670.json)": {"start": 10, "end": null}, "(99,4732.json)": {"start": 11, "end": null}, "(46,4732.json)": {"start": 11, "end": null}, "(5,4732.json)": {"start": 11, "end": null}, "(107,4732.json)": {"start": 11, "end": null}, "(22,4732.json)": {"start": 11, "end": null}, "(29,4732.json)": {"start": 11, "end": null}, "(35,4732.json)": {"start": 11, "end": null}, "(116,4732.json)": {"start": 11, "end": null}, "(65,4732.json)": {"start": 11, "end": null}, "(110,4732.json)": {"start": 11, "end": null}, "(94,4732.json)": {"start": 11, "end": null}, "(105,4732.json)": {"start": 11, "end": null}, "(124,4732.json)": {"start": 11, "end": null}, "(128,4732.json)": {"start": 11, "end": null}, "(56,4732.json)": {"start": 11, "end": null}, "(119,4732.json)": {"start": 11, "end": null}, "(133,4732.json)": {"start": 11, "end": null}, "(66,4732.json)": {"start": 11, "end": null}, "(136,4732.json)": {"start": 11, "end": null}, "(4,4732.json)": {"start": 11, "end": null}, "(99,5235.json)": {"start": 13, "end": 14}, "(46,5235.json)": {"start": 13, "end": 14}, "(5,5235.json)": {"start": 13, "end": 14}, "(107,5235.json)": {"start": 13, "end": 14}, "(22,5235.json)": {"start": 13, "end": 14}, "(29,5235.json)": {"start": 13, "end": 14}, "(35,5235.json)": {"start": 13, "end": 14}, "(116,5235.json)": {"start": 13, "end": 14}, "(65,5235.json)": {"start": 13, "end": 14}, "(110,5235.json)": {"start": 13, "end": 14}, "(94,5235.json)": {"start": 13, "end": 14}, "(105,5235.json)": {"start": 13, "end": 14}, "(124,5235.json)": {"start": 13, "end": 14}, "(128,5235.json)": {"start": 13, "end": 14}, "(56,5235.json)": {"start": 13, "end": 14}, "(119,5235.json)": {"start": 13, "end": 14}, "(133,5235.json)": {"start": 13, "end": 14}, "(66,5235.json)": {"start": 13, "end": 14}, "(136,5235.json)": {"start": 13, "end": 14}, "(4,5235.json)": {"start": 13, "end": 14}, "(78,5886.json)": {"start": 14, "end": null}, "(21,5886.json)": {"start": 14, "end": null}, "(16,5886.json)": {"start": 14, "end": null}, "(92,5886.json)": {"start": 14, "end": null}, "(14,5886.json)": {"start": 14, "end": null}, "(1,5886.json)": {"start": 14, "end": null}, "(91,5886.json)": {"start": 14, "end": null}}