{"(95,7539.json)": {"start": 0, "end": null}, "(110,7539.json)": {"start": 0, "end": null}, "(127,7539.json)": {"start": 0, "end": null}, "(59,7539.json)": {"start": 0, "end": null}, "(90,7539.json)": {"start": 0, "end": null}, "(58,7539.json)": {"start": 0, "end": null}, "(123,7539.json)": {"start": 0, "end": null}, "(105,7539.json)": {"start": 0, "end": null}, "(53,7539.json)": {"start": 0, "end": null}, "(26,7539.json)": {"start": 0, "end": null}, "(125,7539.json)": {"start": 0, "end": null}, "(86,7539.json)": {"start": 0, "end": null}, "(117,7539.json)": {"start": 0, "end": null}, "(91,7539.json)": {"start": 0, "end": null}, "(40,7539.json)": {"start": 0, "end": null}, "(94,7539.json)": {"start": 0, "end": null}, "(15,7539.json)": {"start": 0, "end": null}, "(80,7539.json)": {"start": 0, "end": null}, "(34,7539.json)": {"start": 0, "end": null}, "(13,7539.json)": {"start": 0, "end": null}, "(131,7539.json)": {"start": 0, "end": null}, "(0,7539.json)": {"start": 0, "end": null}, "(25,1218.json)": {"start": 2, "end": null}, "(41,1218.json)": {"start": 2, "end": null}, "(28,1218.json)": {"start": 2, "end": null}, "(46,1218.json)": {"start": 2, "end": null}, "(33,1218.json)": {"start": 2, "end": null}, "(25,10967.json)": {"start": 3, "end": null}, "(41,10967.json)": {"start": 3, "end": null}, "(28,10967.json)": {"start": 3, "end": null}, "(46,10967.json)": {"start": 3, "end": null}, "(33,10967.json)": {"start": 3, "end": null}, "(25,403.json)": {"start": 4, "end": null}, "(41,403.json)": {"start": 4, "end": null}, "(28,403.json)": {"start": 4, "end": null}, "(46,403.json)": {"start": 4, "end": null}, "(33,403.json)": {"start": 4, "end": null}, "(95,2938.json)": {"start": 6, "end": null}, "(25,12575.json)": {"start": 6, "end": null}, "(41,12575.json)": {"start": 6, "end": null}, "(28,12575.json)": {"start": 6, "end": null}, "(46,12575.json)": {"start": 6, "end": null}, "(110,2938.json)": {"start": 6, "end": null}, "(127,2938.json)": {"start": 6, "end": null}, "(59,2938.json)": {"start": 6, "end": null}, "(90,2938.json)": {"start": 6, "end": null}, "(58,2938.json)": {"start": 6, "end": null}, "(33,12575.json)": {"start": 6, "end": null}, "(123,2938.json)": {"start": 6, "end": null}, "(105,2938.json)": {"start": 6, "end": null}, "(53,2938.json)": {"start": 6, "end": null}, "(26,2938.json)": {"start": 6, "end": null}, "(125,2938.json)": {"start": 6, "end": null}, "(86,2938.json)": {"start": 6, "end": null}, "(117,2938.json)": {"start": 6, "end": null}, "(91,2938.json)": {"start": 6, "end": null}, "(40,2938.json)": {"start": 6, "end": null}, "(94,2938.json)": {"start": 6, "end": null}, "(15,2938.json)": {"start": 6, "end": null}, "(80,2938.json)": {"start": 6, "end": null}, "(34,2938.json)": {"start": 6, "end": null}, "(13,2938.json)": {"start": 6, "end": null}, "(131,2938.json)": {"start": 6, "end": null}, "(0,2938.json)": {"start": 6, "end": null}, "(25,4083.json)": {"start": 7, "end": null}, "(41,4083.json)": {"start": 7, "end": null}, "(28,4083.json)": {"start": 7, "end": null}, "(46,4083.json)": {"start": 7, "end": null}, "(33,4083.json)": {"start": 7, "end": null}, "(25,11241.json)": {"start": 10, "end": 10}, "(41,11241.json)": {"start": 10, "end": 10}, "(28,11241.json)": {"start": 10, "end": 10}, "(46,11241.json)": {"start": 10, "end": 10}, "(33,11241.json)": {"start": 10, "end": 10}, "(95,8644.json)": {"start": 12, "end": null}, "(110,8644.json)": {"start": 12, "end": null}, "(127,8644.json)": {"start": 12, "end": null}, "(59,8644.json)": {"start": 12, "end": null}, "(90,8644.json)": {"start": 12, "end": null}, "(58,8644.json)": {"start": 12, "end": null}, "(123,8644.json)": {"start": 12, "end": null}, "(105,8644.json)": {"start": 12, "end": null}, "(53,8644.json)": {"start": 12, "end": null}, "(26,8644.json)": {"start": 12, "end": null}, "(125,8644.json)": {"start": 12, "end": null}, "(86,8644.json)": {"start": 12, "end": null}, "(117,8644.json)": {"start": 12, "end": null}, "(91,8644.json)": {"start": 12, "end": null}, "(40,8644.json)": {"start": 12, "end": null}, "(94,8644.json)": {"start": 12, "end": null}, "(15,8644.json)": {"start": 12, "end": null}, "(80,8644.json)": {"start": 12, "end": null}, "(34,8644.json)": {"start": 12, "end": null}, "(13,8644.json)": {"start": 12, "end": null}, "(131,8644.json)": {"start": 12, "end": null}, "(0,8644.json)": {"start": 12, "end": null}, "(25,6244.json)": {"start": 13, "end": 13}, "(41,6244.json)": {"start": 13, "end": 13}, "(28,6244.json)": {"start": 13, "end": 13}, "(46,6244.json)": {"start": 13, "end": 13}, "(33,6244.json)": {"start": 13, "end": 13}}