{"139": {"start": 0, "end": 2}, "90": {"start": 0, "end": 2}, "93": {"start": 0, "end": 2}, "106": {"start": 0, "end": 2}, "27": {"start": 1, "end": 1}, "88": {"start": 1, "end": 1}, "49": {"start": 1, "end": 1}, "87": {"start": 1, "end": 1}, "132": {"start": 1, "end": 1}, "65": {"start": 1, "end": 1}, "35": {"start": 1, "end": 1}, "64": {"start": 1, "end": 1}, "147": {"start": 1, "end": 1}, "23": {"start": 1, "end": 1}, "113": {"start": 1, "end": 1}, "84": {"start": 1, "end": 1}, "75": {"start": 1, "end": 1}, "47": {"start": 1, "end": 1}, "42": {"start": 1, "end": 1}, "92": {"start": 1, "end": 1}, "80": {"start": 1, "end": 1}, "63": {"start": 1, "end": 1}, "116": {"start": 1, "end": 1}, "114": {"start": 1, "end": 1}, "31": {"start": 1, "end": 1}, "46": {"start": 1, "end": 1}, "18": {"start": 1, "end": 1}}