{"118": {"start": 1, "end": null}, "84": {"start": 1, "end": null}, "31": {"start": 1, "end": null}, "21": {"start": 1, "end": null}, "32": {"start": 1, "end": null}, "28": {"start": 1, "end": null}, "43": {"start": 1, "end": null}, "40": {"start": 1, "end": null}, "131": {"start": 1, "end": null}, "8": {"start": 1, "end": null}, "63": {"start": 1, "end": null}, "113": {"start": 1, "end": null}, "123": {"start": 1, "end": null}, "20": {"start": 1, "end": null}, "140": {"start": 1, "end": null}, "134": {"start": 1, "end": null}, "142": {"start": 1, "end": null}, "38": {"start": 1, "end": null}, "25": {"start": 1, "end": null}, "83": {"start": 1, "end": null}, "82": {"start": 3, "end": 14}, "124": {"start": 3, "end": 14}, "18": {"start": 3, "end": 14}, "133": {"start": 3, "end": 14}, "119": {"start": 3, "end": 14}, "50": {"start": 3, "end": 14}, "16": {"start": 3, "end": 14}}