{"(6,11788.json)": {"start": 3, "end": 3}, "(148,11788.json)": {"start": 3, "end": 3}, "(42,11788.json)": {"start": 3, "end": 3}, "(47,11788.json)": {"start": 3, "end": 3}, "(10,11788.json)": {"start": 3, "end": 3}, "(54,11788.json)": {"start": 3, "end": 3}, "(135,11788.json)": {"start": 3, "end": 3}, "(20,11788.json)": {"start": 3, "end": 3}, "(131,11788.json)": {"start": 3, "end": 3}, "(105,11788.json)": {"start": 3, "end": 3}, "(112,11788.json)": {"start": 3, "end": 3}, "(31,11788.json)": {"start": 3, "end": 3}, "(16,11788.json)": {"start": 3, "end": 3}, "(44,11788.json)": {"start": 3, "end": 3}, "(80,11788.json)": {"start": 3, "end": 3}, "(118,11788.json)": {"start": 3, "end": 3}, "(124,11788.json)": {"start": 3, "end": 3}, "(66,11788.json)": {"start": 3, "end": 3}, "(18,11788.json)": {"start": 3, "end": 3}, "(69,11788.json)": {"start": 3, "end": 3}, "(60,11788.json)": {"start": 3, "end": 3}, "(6,9206.json)": {"start": 11, "end": 11}, "(148,9206.json)": {"start": 11, "end": 11}, "(42,9206.json)": {"start": 11, "end": 11}, "(47,9206.json)": {"start": 11, "end": 11}, "(10,9206.json)": {"start": 11, "end": 11}, "(54,9206.json)": {"start": 11, "end": 11}, "(135,9206.json)": {"start": 11, "end": 11}, "(20,9206.json)": {"start": 11, "end": 11}, "(131,9206.json)": {"start": 11, "end": 11}, "(105,9206.json)": {"start": 11, "end": 11}, "(112,9206.json)": {"start": 11, "end": 11}, "(31,9206.json)": {"start": 11, "end": 11}, "(16,9206.json)": {"start": 11, "end": 11}, "(44,9206.json)": {"start": 11, "end": 11}, "(80,9206.json)": {"start": 11, "end": 11}, "(118,9206.json)": {"start": 11, "end": 11}, "(124,9206.json)": {"start": 11, "end": 11}, "(66,9206.json)": {"start": 11, "end": 11}, "(18,9206.json)": {"start": 11, "end": 11}, "(69,9206.json)": {"start": 11, "end": 11}, "(60,9206.json)": {"start": 11, "end": 11}, "(8,13114.json)": {"start": 13, "end": 13}, "(70,13114.json)": {"start": 13, "end": 13}, "(48,13114.json)": {"start": 13, "end": 13}, "(57,13114.json)": {"start": 13, "end": 13}, "(138,13114.json)": {"start": 13, "end": 13}, "(75,13114.json)": {"start": 13, "end": 13}}